pypiage.py
pypiage-0.1.5.dist-info/METADATA
pypiage-0.1.5.dist-info/WHEEL
pypiage-0.1.5.dist-info/entry_points.txt
pypiage-0.1.5.dist-info/top_level.txt
pypiage-0.1.5.dist-info/RECORD
