Metadata-Version: 2.1
Name: pypiage
Version: 0.1.5
Summary: A package for finding the least updated packages your project depends on.
Home-page: https://github.com/KarmaComputing/pypiage
Author: chrisjsimpson
Author-email: oss@karmacomputing.co.uk
License: UNKNOWN
Platform: UNKNOWN
Classifier: Programming Language :: Python :: 3
Classifier: License :: OSI Approved :: MIT License
Classifier: Operating System :: OS Independent
Requires-Python: >=3.6
